{
  "status": "success",
  "analysis": {
    "ticker": "V",
    "name": "V",
    "category": "sp500",
    "price": 357.2300109863281,
    "currency": "USD",
    "score": 46.7,
    "profile": "conservador",
    "horizon": "long",
    "technical": [
      {
        "title": "RSI (Índice de Fuerza Relativa)",
        "icon": "fa-gauge-high",
        "content": "El RSI de 14 períodos se encuentra en 70.6, lo que indica una zona de **sobrecompra**. Históricamente, un RSI por encima de 70 sugiere que el activo podría experimentar una corrección a la baja en el corto plazo. Se recomienda cautela para nuevas entradas.",
        "value": "70.6",
        "status": "warning"
      },
      {
        "title": "Cruce de Medias Móviles (EMA 50/200)",
        "icon": "fa-chart-line",
        "content": "La EMA de 50 días (328.39) se encuentra por encima de la EMA de 200 días (326.24), y el precio actual (357.23) supera ambas medias. Esta configuración se denomina **Golden Cross activo** y es una señal técnica fuertemente alcista para el mediano plazo.",
        "value": "Fuerte Alcista",
        "status": "success"
      },
      {
        "title": "Volatilidad Anualizada",
        "icon": "fa-wave-square",
        "content": "La volatilidad anualizada es de **22.4%**, ubicándose en un rango **moderado**. Este nivel es compatible con inversiones de mediano plazo siempre que se acompañe de un buen ratio de Sharpe.",
        "value": "22.4%",
        "status": "neutral"
      },
      {
        "title": "Momentum de Corto Plazo",
        "icon": "fa-bolt",
        "content": "El activo registró un rendimiento del **+11.6%** en el último mes, mostrando un **fuerte momentum alcista**. Los retornos de 3 meses (18.0%) refuerzan esta tendencia positiva.",
        "value": "+11.6% (1M)",
        "status": "success"
      },
      {
        "title": "Estructura de Precios (Soporte/Resistencia/Volumen)",
        "icon": "fa-chart-area",
        "content": "El análisis de la estructura de precios ubica los niveles clave del activo:\n- **Soporte de mediano plazo:** USD 302.62 (zona histórica de compra).\n- **Resistencia de largo plazo:** USD 332.27 (zona histórica de toma de ganancias).\n- **Precio Clave del Volumen (POC):** USD 325.16. Este nivel representa el precio más operado del trimestre, operando como un pivote de estabilidad de volumen.",
        "value": "POC: 325.16",
        "status": "success"
      }
    ],
    "fundamental": [
      {
        "title": "Ratio de Sharpe (Riesgo/Retorno)",
        "icon": "fa-scale-balanced",
        "content": "**¿Qué mide?** El Ratio de Sharpe responde a la pregunta: _¿cuánto rendimiento extra obtengo por cada unidad de riesgo que asumo?_ Compara el retorno del activo contra la **tasa libre de riesgo** (lo que ganarías sin arriesgar nada). Un valor positivo indica que el activo rinde más de lo mínimo esperado; un valor negativo indica que **no conviene asumir ese riesgo**, porque rendirías menos que dejando el dinero en un instrumento seguro.\n\nEl Ratio de Sharpe de este activo es **-0.16** (negativo): el retorno del activo **no alcanza ni la tasa libre de riesgo**. En términos prácticos, el inversor destruye valor ajustado por riesgo: asumir esta volatilidad no está siendo recompensado.",
        "value": "-0.16",
        "status": "danger"
      },
      {
        "title": "Rendimiento Acumulado (Mediano Plazo)",
        "icon": "fa-arrow-trend-up",
        "content": "El rendimiento acumulado a 6 meses es **+3.5%** y a 12 meses es **+0.3%**. Los retornos son **positivos pero moderados**, alineados con un contexto de crecimiento gradual.",
        "value": "+3.5% (6M)",
        "status": "neutral"
      },
      {
        "title": "Comparativa de Inflación Argentina",
        "icon": "fa-fire-flame-curved",
        "content": "El retorno estimado en pesos para este activo en un horizonte de **largo plazo (más de 1 año)** es del **102.7%**, superando la inflación proyectada del período del **47.0%** con un spread real positivo de **+55.7%**. Cumple con el objetivo de preservar y acrecentar el poder adquisitivo.",
        "value": "Retorno Est.: 102.7%",
        "status": "success"
      }
    ],
    "macro": [
      {
        "title": "Entorno de Mercados Internacionales (EE.UU.)",
        "icon": "fa-globe",
        "content": "**Contexto EE.UU. (Jul 2026):** La Reserva Federal mantiene una postura de política monetaria que equilibra el control inflacionario con el sostenimiento del empleo. Los mercados de renta variable estadounidenses han mostrado resiliencia, impulsados por el sector tecnológico y la inteligencia artificial. Los CEDEARs permiten al inversor argentino acceder a estas dinámicas con cobertura implícita en dólares (tipo de cambio CCL). El ratio P/E del S&P 500 se encuentra por encima de su promedio histórico, lo que sugiere valuaciones exigentes que podrían limitar el upside de corto plazo.",
        "status": "neutral"
      }
    ],
    "balances": {
      "snapshots": [
        {
          "period": "Mar 2026",
          "revenue_b": 11.23,
          "net_income_b": 6.02,
          "net_margin_pct": 53.6,
          "eps": null,
          "fcf_b": 2.62,
          "debt_equity": 0.67,
          "favorable": [
            "Margen neto sólido del 53.6%",
            "FCF positivo: $2.6B"
          ],
          "critical": []
        },
        {
          "period": "Dec 2025",
          "revenue_b": 10.9,
          "net_income_b": 5.85,
          "net_margin_pct": 53.7,
          "eps": null,
          "fcf_b": 6.4,
          "debt_equity": 0.55,
          "favorable": [
            "Margen neto sólido del 53.7%",
            "FCF positivo: $6.4B"
          ],
          "critical": []
        },
        {
          "period": "Sep 2025",
          "revenue_b": 10.72,
          "net_income_b": 5.09,
          "net_margin_pct": 47.5,
          "eps": null,
          "fcf_b": 5.85,
          "debt_equity": 0.66,
          "favorable": [
            "Margen neto sólido del 47.5%",
            "FCF positivo: $5.8B"
          ],
          "critical": []
        },
        {
          "period": "Jun 2025",
          "revenue_b": 10.17,
          "net_income_b": 5.27,
          "net_margin_pct": 51.8,
          "eps": null,
          "fcf_b": 6.31,
          "debt_equity": 0.65,
          "favorable": [
            "Margen neto sólido del 51.8%",
            "FCF positivo: $6.3B"
          ],
          "critical": [
            "Ingresos en baja vs trimestre anterior: -5.1%"
          ]
        },
        {
          "period": "Mar 2025",
          "revenue_b": 9.59,
          "net_income_b": 4.58,
          "net_margin_pct": 47.8,
          "eps": null,
          "fcf_b": 4.37,
          "debt_equity": 0.55,
          "favorable": [
            "Margen neto sólido del 47.8%",
            "FCF positivo: $4.4B"
          ],
          "critical": [
            "Ingresos en baja vs trimestre anterior: -5.7%"
          ]
        }
      ],
      "summary": {
        "periods_analyzed": 5,
        "avg_revenue_b": 10.52,
        "avg_net_margin_pct": 50.9,
        "avg_eps": null,
        "revenue_trend": "creciente",
        "margin_trend": "en expansión",
        "total_favorable_signals": 10,
        "total_critical_signals": 2,
        "conclusion": "ESTABLE",
        "conclusion_color": "neutral",
        "conclusion_detail": "Los últimos 5 balances presentan estabilidad general con ingresos crecientes y margen promedio del 50.9%. Hay 2 señales de atención y 10 puntos positivos. Perfil de riesgo moderado."
      }
    },
    "verdict": {
      "action": "CAUTELA",
      "icon": "fa-triangle-exclamation",
      "color": "warning",
      "summary": "El score de **46.7/100** indica que este activo no es ideal para el perfil **conservador**. La tendencia técnica es favorable y acompaña la recomendación. El ratio de Sharpe negativo sugiere que el retorno no justifica la volatilidad. El RSI en zona de sobrecompra aconseja esperar una corrección antes de entrar.",
      "take_profit": 472.54,
      "stop_loss": 305.98,
      "tp_pct": 32.3,
      "sl_pct": 14.3
    },
    "support": 302.62,
    "resistance": 332.27,
    "volume_cluster": 325.16,
    "take_profit": 472.54,
    "stop_loss": 305.98,
    "tp_pct": 32.3,
    "sl_pct": 14.3
  }
}