{
  "status": "success",
  "scan_date": "2026-07-18",
  "total_new_discoveries": 8,
  "categories": {
    "sp500": [
      {
        "ticker": "JNJ",
        "name": "JNJ",
        "category": "sp500",
        "price": 253.04,
        "currency": "USD",
        "ret_1m": 0.0804,
        "ret_3m": 0.0868,
        "ret_6m": 0.1652,
        "ret_12m": 0.5914,
        "volatility": 0.1966,
        "sharpe": 2.8,
        "rsi": 48.6,
        "ema_50": 243.0886,
        "ema_200": 220.8599,
        "ema_200_slope": 0.0425,
        "ema_cross_signal": 0.1006,
        "trend": "Fuerte Alcista",
        "momentum_accel": -0.0063,
        "support": 224.0,
        "resistance": 254.05,
        "dist_to_support_pct": 0.1148,
        "dist_to_resistance_pct": 0.004,
        "vol_short_vs_long": 1.6808,
        "drawdown_pct": 0.0531,
        "high_52w": 267.24,
        "dollar_vol_20d": 2336007261.0,
        "atr_pct": 0.026,
        "timestamp": 1784415544.6738954,
        "funnel_score": 82.9,
        "desglose": {
          "tendencia": 93.6,
          "momentum": 81.0,
          "volumen_relativo": 100.0,
          "valuacion": 82.6,
          "riesgo": 30.8,
          "patron_velas": {
            "patron_detectado": "sin_patron",
            "fuerza_base": 0.0,
            "contexto_mult": 1.0,
            "contexto_descripcion": "sin_contexto_adicional",
            "descripcion": "Sin patrón de velas relevante detectado",
            "valor": 50.0,
            "bonus_pts": 0.0,
            "peso_aplicado": "10%"
          }
        },
        "profile": "conservador",
        "horizon": "long"
      },
      {
        "ticker": "XLV",
        "name": "XLV",
        "category": "sp500",
        "price": 161.09,
        "currency": "USD",
        "ret_1m": 0.0736,
        "ret_3m": 0.0874,
        "ret_6m": 0.0351,
        "ret_12m": 0.235,
        "volatility": 0.1719,
        "sharpe": 1.13,
        "rsi": 51.6,
        "ema_50": 154.5977,
        "ema_200": 149.2046,
        "ema_200_slope": 0.0181,
        "ema_cross_signal": 0.0361,
        "trend": "Fuerte Alcista",
        "momentum_accel": -0.0138,
        "support": 144.09,
        "resistance": 160.75,
        "dist_to_support_pct": 0.1055,
        "dist_to_resistance_pct": -0.0021,
        "vol_short_vs_long": 1.283,
        "drawdown_pct": 0.0204,
        "high_52w": 164.44,
        "dollar_vol_20d": 1783167792.0,
        "atr_pct": 0.0174,
        "timestamp": 1784415545.7162743,
        "funnel_score": 67.4,
        "desglose": {
          "tendencia": 82.2,
          "momentum": 62.3,
          "volumen_relativo": 100.0,
          "valuacion": 67.4,
          "riesgo": 30.7,
          "patron_velas": {
            "patron_detectado": "shooting_star",
            "fuerza_base": 1.0,
            "contexto_mult": 1.2,
            "contexto_descripcion": "confirmado",
            "descripcion": "Estrella fugaz: sombra superior larga en zona de resistencia",
            "valor": 0.0,
            "bonus_pts": -5.0,
            "peso_aplicado": "10%"
          }
        },
        "profile": "conservador",
        "horizon": "long"
      },
      {
        "ticker": "KO",
        "name": "KO",
        "category": "sp500",
        "price": 81.56,
        "currency": "USD",
        "ret_1m": 0.0204,
        "ret_3m": 0.0838,
        "ret_6m": 0.1727,
        "ret_12m": 0.1881,
        "volatility": 0.1846,
        "sharpe": 0.8,
        "rsi": 46.9,
        "ema_50": 80.8131,
        "ema_200": 75.5579,
        "ema_200_slope": 0.029,
        "ema_cross_signal": 0.0696,
        "trend": "Fuerte Alcista",
        "momentum_accel": -0.0634,
        "support": 74.94,
        "resistance": 82.68,
        "dist_to_support_pct": 0.0811,
        "dist_to_resistance_pct": 0.0137,
        "vol_short_vs_long": 1.5052,
        "drawdown_pct": 0.0396,
        "high_52w": 84.92,
        "dollar_vol_20d": 1716798085.0,
        "atr_pct": 0.024,
        "timestamp": 1784415544.7170668,
        "funnel_score": 65.6,
        "desglose": {
          "tendencia": 87.8,
          "momentum": 53.8,
          "volumen_relativo": 100.0,
          "valuacion": 61.7,
          "riesgo": 34.1,
          "patron_velas": {
            "patron_detectado": "bearish_engulfing",
            "fuerza_base": 1.0,
            "contexto_mult": 1.56,
            "contexto_descripcion": "vol×1.6, confirmado",
            "descripcion": "Envolvente bajista: vela bajista que supera la alcista anterior",
            "valor": 0.0,
            "bonus_pts": -5.0,
            "peso_aplicado": "10%"
          }
        },
        "profile": "conservador",
        "horizon": "long"
      },
      {
        "ticker": "XLF",
        "name": "XLF",
        "category": "sp500",
        "price": 56.26,
        "currency": "USD",
        "ret_1m": 0.0445,
        "ret_3m": 0.0768,
        "ret_6m": 0.0437,
        "ret_12m": 0.088,
        "volatility": 0.182,
        "sharpe": 0.26,
        "rsi": 71.6,
        "ema_50": 53.6551,
        "ema_200": 52.2048,
        "ema_200_slope": 0.0145,
        "ema_cross_signal": 0.0278,
        "trend": "Fuerte Alcista",
        "momentum_accel": -0.0323,
        "support": 49.08,
        "resistance": 55.55,
        "dist_to_support_pct": 0.1277,
        "dist_to_resistance_pct": -0.0127,
        "vol_short_vs_long": 0.7866,
        "drawdown_pct": 0.0086,
        "high_52w": 56.75,
        "dollar_vol_20d": 1898084532.0,
        "atr_pct": 0.0134,
        "timestamp": 1784415545.6967952,
        "funnel_score": 65.4,
        "desglose": {
          "tendencia": 80.7,
          "momentum": 41.5,
          "volumen_relativo": 100.0,
          "valuacion": 57.7,
          "riesgo": 28.0,
          "patron_velas": {
            "patron_detectado": "sin_patron",
            "fuerza_base": 0.0,
            "contexto_mult": 1.0,
            "contexto_descripcion": "sin_contexto_adicional",
            "descripcion": "Sin patrón de velas relevante detectado",
            "valor": 50.0,
            "bonus_pts": 0.0,
            "peso_aplicado": "10%"
          }
        },
        "profile": "conservador",
        "horizon": "long"
      },
      {
        "ticker": "XLU",
        "name": "XLU",
        "category": "sp500",
        "price": 45.17,
        "currency": "USD",
        "ret_1m": 0.0225,
        "ret_3m": -0.0152,
        "ret_6m": 0.0497,
        "ret_12m": 0.1273,
        "volatility": 0.1595,
        "sharpe": 0.55,
        "rsi": 40.6,
        "ema_50": 45.0302,
        "ema_200": 43.9735,
        "ema_200_slope": 0.008,
        "ema_cross_signal": 0.024,
        "trend": "Fuerte Alcista",
        "momentum_accel": 0.0377,
        "support": 43.77,
        "resistance": 46.18,
        "dist_to_support_pct": 0.0311,
        "dist_to_resistance_pct": 0.0223,
        "vol_short_vs_long": 0.9499,
        "drawdown_pct": 0.0409,
        "high_52w": 47.1,
        "dollar_vol_20d": 910140499.0,
        "atr_pct": 0.0155,
        "timestamp": 1784415545.6766355,
        "funnel_score": 63.8,
        "desglose": {
          "tendencia": 79.0,
          "momentum": 52.5,
          "volumen_relativo": 100.0,
          "valuacion": 60.3,
          "riesgo": 40.1,
          "patron_velas": {
            "patron_detectado": "bearish_engulfing",
            "fuerza_base": 1.0,
            "contexto_mult": 1.2,
            "contexto_descripcion": "confirmado",
            "descripcion": "Envolvente bajista: vela bajista que supera la alcista anterior",
            "valor": 0.0,
            "bonus_pts": -5.0,
            "peso_aplicado": "10%"
          }
        },
        "profile": "conservador",
        "horizon": "long"
      }
    ],
    "cedears": [
      {
        "ticker": "GOOGL.BA",
        "name": "GOOGL",
        "category": "cedears",
        "price": 9420.0,
        "currency": "ARS",
        "ret_1m": -0.0264,
        "ret_3m": 0.0915,
        "ret_6m": 0.0884,
        "ret_12m": 1.3288,
        "volatility": 0.3761,
        "sharpe": 3.43,
        "rsi": 49.1,
        "ema_50": 9497.8591,
        "ema_200": 8221.2204,
        "ema_200_slope": 0.0579,
        "ema_cross_signal": 0.1553,
        "trend": "Alcista",
        "momentum_accel": -0.1179,
        "support": 7659.0,
        "resistance": 9983.0,
        "dist_to_support_pct": 0.1869,
        "dist_to_resistance_pct": 0.0598,
        "vol_short_vs_long": 0.9796,
        "drawdown_pct": 0.0837,
        "high_52w": 10280.0,
        "dollar_vol_20d": 2405214749.0,
        "atr_pct": 0.0291,
        "timestamp": 1784415545.7831504,
        "funnel_score": 56.7,
        "desglose": {
          "tendencia": 85.0,
          "momentum": 74.7,
          "volumen_relativo": 100.0,
          "valuacion": 72.2,
          "riesgo": 32.7,
          "patron_velas": {
            "patron_detectado": "doji",
            "fuerza_base": 0.3,
            "contexto_mult": 1.0,
            "contexto_descripcion": "sin_contexto_adicional",
            "descripcion": "Doji: indecisión del mercado, cuerpo mínimo",
            "valor": 50.0,
            "bonus_pts": 0.0,
            "peso_aplicado": "10%"
          }
        },
        "profile": "conservador",
        "horizon": "long"
      },
      {
        "ticker": "GS.BA",
        "name": "GS",
        "category": "cedears",
        "price": 129675.0,
        "currency": "ARS",
        "ret_1m": -0.0023,
        "ret_3m": 0.2248,
        "ret_6m": 0.1486,
        "ret_12m": 0.8767,
        "volatility": 0.3814,
        "sharpe": 2.19,
        "rsi": 60.4,
        "ema_50": 121774.5293,
        "ema_200": 104522.3919,
        "ema_200_slope": 0.076,
        "ema_cross_signal": 0.1651,
        "trend": "Fuerte Alcista",
        "momentum_accel": -0.2271,
        "support": 92094.73,
        "resistance": 127900.0,
        "dist_to_support_pct": 0.2898,
        "dist_to_resistance_pct": -0.0137,
        "vol_short_vs_long": 1.1681,
        "drawdown_pct": 0.0649,
        "high_52w": 138675.0,
        "dollar_vol_20d": 130727992.0,
        "atr_pct": 0.0299,
        "timestamp": 1784415545.8535967,
        "funnel_score": 55.4,
        "desglose": {
          "tendencia": 100.0,
          "momentum": 75.1,
          "volumen_relativo": 100.0,
          "valuacion": 63.9,
          "riesgo": 17.6,
          "patron_velas": {
            "patron_detectado": "sin_patron",
            "fuerza_base": 0.0,
            "contexto_mult": 1.0,
            "contexto_descripcion": "sin_contexto_adicional",
            "descripcion": "Sin patrón de velas relevante detectado",
            "valor": 50.0,
            "bonus_pts": 0.0,
            "peso_aplicado": "10%"
          }
        },
        "profile": "conservador",
        "horizon": "long"
      },
      {
        "ticker": "CSCO.BA",
        "name": "CSCO",
        "category": "cedears",
        "price": 35460.0,
        "currency": "ARS",
        "ret_1m": -0.0134,
        "ret_3m": 0.3483,
        "ret_6m": 0.5594,
        "ret_12m": 1.0119,
        "volatility": 0.3898,
        "sharpe": 2.49,
        "rsi": 45.3,
        "ema_50": 34552.6591,
        "ema_200": 27563.2651,
        "ema_200_slope": 0.1177,
        "ema_cross_signal": 0.2536,
        "trend": "Fuerte Alcista",
        "momentum_accel": -0.3616,
        "support": 23029.86,
        "resistance": 36827.91,
        "dist_to_support_pct": 0.3505,
        "dist_to_resistance_pct": 0.0386,
        "vol_short_vs_long": 1.1511,
        "drawdown_pct": 0.0982,
        "high_52w": 39319.91,
        "dollar_vol_20d": 107389634.0,
        "atr_pct": 0.0361,
        "timestamp": 1784415545.8640196,
        "funnel_score": 55.3,
        "desglose": {
          "tendencia": 100.0,
          "momentum": 71.3,
          "volumen_relativo": 100.0,
          "valuacion": 64.7,
          "riesgo": 19.9,
          "patron_velas": {
            "patron_detectado": "sin_patron",
            "fuerza_base": 0.0,
            "contexto_mult": 1.3,
            "contexto_descripcion": "vol×2.5",
            "descripcion": "Sin patrón de velas relevante detectado",
            "valor": 50.0,
            "bonus_pts": 0.0,
            "peso_aplicado": "10%"
          }
        },
        "profile": "conservador",
        "horizon": "long"
      }
    ],
    "merval": [],
    "crypto": []
  },
  "pipeline": {
    "universe_size": 270,
    "stage1_passed": 248,
    "stage2_passed": 146,
    "final_count": 8,
    "timestamp": 1784415542.7402852,
    "profile": "conservador",
    "horizon": "long"
  }
}