{
  "status": "success",
  "optimization": {
    "weights": [
      {
        "ticker": "MRK",
        "name": "MRK",
        "category": "sp500",
        "currency": "USD",
        "weight": 0.4389,
        "weight_pct": 43.9,
        "ars_return_est": 37.6
      },
      {
        "ticker": "HD",
        "name": "HD",
        "category": "sp500",
        "currency": "USD",
        "weight": 0.2167,
        "weight_pct": 21.7,
        "ars_return_est": 18.6
      },
      {
        "ticker": "XOM.BA",
        "name": "XOM",
        "category": "cedears",
        "currency": "ARS",
        "weight": 0.2,
        "weight_pct": 20.0,
        "ars_return_est": 17.2
      },
      {
        "ticker": "META",
        "name": "META",
        "category": "sp500",
        "currency": "USD",
        "weight": 0.1444,
        "weight_pct": 14.4,
        "ars_return_est": 12.4
      }
    ],
    "expected_return": 25.77,
    "expected_volatility": 24.18,
    "sharpe_ratio": 0.61,
    "profile": "conservador",
    "horizon": "short",
    "risk_free_rate": 11.0,
    "inflation_reference": 11.0,
    "beats_inflation": true,
    "spread_vs_inflation": 14.8
  }
}